pangolinn/__init__.py
pangolinn/seq2seq/__init__.py
pangolinn/seq2seq/base_tester.py
pangolinn/seq2seq/causal_tester.py
pangolinn/seq2seq/padding_tester.py
pangolinn/seq2seq/seq2seq_module_wrapper.py
pangolinn-0.0.1.dist-info/LICENSE
pangolinn-0.0.1.dist-info/METADATA
pangolinn-0.0.1.dist-info/WHEEL
pangolinn-0.0.1.dist-info/top_level.txt
pangolinn-0.0.1.dist-info/RECORD
