Metadata-Version: 2.1
Name: pangolinn
Version: 0.0.1
Summary: Helper library with tests that check common issues in neural network models.
Author-email: Marco Gaido <mgaido@fbk.eu>, Sara Papi <spapi@fbk.eu>
Project-URL: Homepage, https://github.com/hlt-mt/pangolinn
Project-URL: Bug Tracker, https://github.com/hlt-mt/pangolinn/issues
Classifier: Programming Language :: Python :: 3
Classifier: License :: OSI Approved :: Apache Software License
Classifier: Operating System :: OS Independent
Classifier: Topic :: Scientific/Engineering :: Artificial Intelligence
Classifier: Topic :: Software Development :: Testing :: Unit
Requires-Python: >=3.8
License-File: LICENSE
Requires-Dist: torch
Requires-Dist: pytest
Provides-Extra: dev
Requires-Dist: flake8 ; extra == 'dev'
Requires-Dist: numpy ; extra == 'dev'
Provides-Extra: release
Requires-Dist: build ; extra == 'release'
Requires-Dist: twine ; extra == 'release'
Requires-Dist: sphinx ; extra == 'release'
Requires-Dist: sphinx-rtd-theme ; extra == 'release'
